README.md
setup.py
joystick_jhr.egg-info/PKG-INFO
joystick_jhr.egg-info/SOURCES.txt
joystick_jhr.egg-info/dependency_links.txt
joystick_jhr.egg-info/top_level.txt
joystickjhr/__init__.py
joystickjhr/joystickJhr.py