Metadata-Version: 2.1
Name: joystick-jhr
Version: 0.2.0
Summary: joystick jhr python multiuso
Home-page: https://github.com/jose-jhr/Joystick-jhr-python
Download-URL: https://github.com/jose-jhr/Joystick-jhr-python/tarball/0.2
Author: Jose Hidalgo
License: MIT
Keywords: joystick,python jhr,jhr,ingenieria jhr
